voiceprint_recognition/Container.py
voiceprint_recognition/Engine.py
voiceprint_recognition/__init__.py
VoiceprintRecognition-0.1.0.dist-info/METADATA
VoiceprintRecognition-0.1.0.dist-info/WHEEL
VoiceprintRecognition-0.1.0.dist-info/top_level.txt
VoiceprintRecognition-0.1.0.dist-info/RECORD
