Metadata-Version: 2.1
Name: VoiceprintRecognition
Version: 0.1.0
Summary: A speaker recognition library that works both online and offline and supports a number of engines and APIs. 
Home-page: https://github.com/SriBalajiSMVEC/voiceprint_recognition
Author: BalajiSanthanam
Author-email: sribalaji2112@gmail.com
License: BSD 3-Clause License
Keywords: biometric speaker recognition voice sphinx google wit bing api houndify ibm snowboy voice print identification security
Classifier: Development Status :: 4 - Beta
Classifier: Environment :: Win32 (MS Windows)
Classifier: Environment :: X11 Applications
Classifier: Environment :: MacOS X
Classifier: Intended Audience :: Developers
Classifier: License :: OSI Approved :: MIT License
Classifier: Operating System :: OS Independent
Classifier: Programming Language :: Python
Classifier: Programming Language :: Python :: 2
Classifier: Programming Language :: Python :: 2.7
Classifier: Programming Language :: Python :: 3
Classifier: Programming Language :: Python :: 3.1
Classifier: Programming Language :: Python :: 3.2
Classifier: Programming Language :: Python :: 3.3
Classifier: Programming Language :: Python :: 3.4
Classifier: Programming Language :: Python :: 3.5
Classifier: Programming Language :: Python :: 3.6
Classifier: Programming Language :: Python :: 3.7
Classifier: Programming Language :: Python :: 3.8
Requires-Dist: pymsgbox
Requires-Dist: pytweening (>=1.0.4)
Requires-Dist: pyscreeze (>=0.1.21)
Requires-Dist: pygetwindow (>=0.0.5)
Requires-Dist: mouseinfo
Requires-Dist: SpeechRecognition
Requires-Dist: keras
Requires-Dist: tensorflow
Requires-Dist: os
Requires-Dist: pyobjc-core ; platform_system == "Darwin"
Requires-Dist: pyobjc ; platform_system == "Darwin"
Requires-Dist: python-xlib ; platform_system == "Linux" and python_version < "3.0"
Requires-Dist: python3-Xlib ; platform_system == "Linux" and python_version >= "3.0"
